uiweb/__init__.py
uiweb/uiweb.py
uiweb/uiweb_.py
uiweb/uiweb_1202.py
uiweb-0.9.80.dist-info/LICENSE
uiweb-0.9.80.dist-info/METADATA
uiweb-0.9.80.dist-info/WHEEL
uiweb-0.9.80.dist-info/top_level.txt
uiweb-0.9.80.dist-info/RECORD
